{
  "date": "2025-07-03",
  "study": {
    "totalMinutes": 295,
    "sessions": [
      {
        "duration": 25,
        "method": "pomodoro",
        "time": "09:47",
        "timestamp": "2025-07-03T01:47:42.110Z"
      },
      {
        "duration": 25,
        "method": "pomodoro",
        "time": "10:18",
        "timestamp": "2025-07-03T02:18:33.230Z"
      },
      {
        "duration": 25,
        "method": "pomodoro",
        "time": "10:56",
        "timestamp": "2025-07-03T02:56:24.972Z"
      },
      {
        "duration": 30,
        "method": "pomodoro",
        "time": "15:50",
        "timestamp": "2025-07-03T07:50:01.138Z"
      },
      {
        "duration": 30,
        "method": "pomodoro",
        "time": "17:01",
        "timestamp": "2025-07-03T09:01:00.182Z"
      },
      {
        "duration": 25,
        "method": "pomodoro",
        "time": "20:49",
        "timestamp": "2025-07-03T12:49:57.443Z"
      },
      {
        "duration": 15,
        "method": "pomodoro",
        "time": "21:10",
        "timestamp": "2025-07-03T13:10:37.587Z"
      },
      {
        "duration": 30,
        "method": "pomodoro",
        "time": "22:00",
        "timestamp": "2025-07-03T14:00:39.292Z"
      },
      {
        "duration": 30,
        "method": "pomodoro",
        "time": "22:39",
        "timestamp": "2025-07-03T14:39:59.818Z"
      },
      {
        "duration": 60,
        "method": "pomodoro",
        "time": "23:57",
        "timestamp": "2025-07-03T15:57:14.181Z"
      }
    ],
    "pomodoroCount": 10
  },
  "exercise": {
    "pullUps": 0,
    "squats": 0,
    "pushUps": 0,
    "running": 0,
    "swimming": 0,
    "cycling": 0,
    "feeling": ""
  },
  "expenses": {
    "breakfast": 0,
    "lunch": 90,
    "dinner": 8.8,
    "customCategories": {},
    "customCategoryNames": {},
    "other": [
      {
        "id": 1751524143140,
        "description": "优衣库，T恤*2，短裤*1",
        "amount": 237,
        "time": "14:29"
      },
      {
        "id": 1751539176560,
        "description": "彩票",
        "amount": 30,
        "time": "18:39"
      }
    ],
    "total": 365.8
  },
  "tasks": [
    {
      "id": 1751505109877,
      "text": "OS第四章",
      "completed": true,
      "pomodoroCount": 7,
      "createdAt": "2025-07-03T01:11:49.877Z"
    },
    {
      "id": 1751505116168,
      "text": "OS第五章",
      "completed": true,
      "pomodoroCount": 2,
      "createdAt": "2025-07-03T01:11:56.168Z"
    },
    {
      "id": 1751505122189,
      "text": "OS第六章",
      "completed": true,
      "pomodoroCount": 1,
      "createdAt": "2025-07-03T01:12:02.189Z"
    },
    {
      "id": 1751505128303,
      "text": "所有计算题",
      "completed": true,
      "pomodoroCount": 0,
      "createdAt": "2025-07-03T01:12:08.303Z"
    },
    {
      "id": 1751505150473,
      "text": "脑图过一遍",
      "completed": true,
      "pomodoroCount": 0,
      "createdAt": "2025-07-03T01:12:30.473Z"
    }
  ],
  "health": {
    "weight": 0,
    "sleepHours": 0,
    "sleepQuality": 0,
    "phoneUsage": 0
  },
  "theme": "dark",
  "importantInfo": "明天早上考操作系统！！！",
  "examDate": "2025-12-20",
  "dayStart": "操作系统复习",
  "dayReflection": "哇，今天有点极限了，现在快1点了，还是没控制住自己。虽然学习时间比以往长，但是还是自制力不足！！\n\n明天计划：\n明早要早点起来，把所有计算题来一遍，然后把脑图过一遍",
  "reflectionTime": "00:47",
  "metadata": {
    "created": "2025-07-03T01:11:23.095Z",
    "lastModified": "2025-07-03T16:47:38.477Z"
  },
  "currentBoundTask": null,
  "pomodoroRunning": false,
  "focusMode": false,
  "focusQuoteIndex": 0,
  "breakMode": false,
  "breakTimeLeft": 300,
  "config": {
    "target": {
      "name": "考研",
      "date": "2025-12-20",
      "dailyGoal": 360
    },
    "exerciseTypes": {
      "pushUps": {
        "enabled": true,
        "name": "俯卧撑"
      },
      "pullUps": {
        "enabled": true,
        "name": "引体向上"
      },
      "squats": {
        "enabled": true,
        "name": "深蹲"
      },
      "swimming": {
        "enabled": false,
        "name": "游泳"
      },
      "cycling": {
        "enabled": false,
        "name": "骑行"
      }
    },
    "expenseCategories": {
      "breakfast": {
        "enabled": false,
        "name": "早餐"
      },
      "lunch": {
        "enabled": true,
        "name": "午餐"
      },
      "dinner": {
        "enabled": true,
        "name": "晚餐"
      },
      "custom": []
    },
    "theme": {
      "mode": "light",
      "color": "blue"
    }
  }
}